print_extended/__init__.py
print_extended/cli.py
print_extended-0.2.0.dist-info/LICENSE
print_extended-0.2.0.dist-info/METADATA
print_extended-0.2.0.dist-info/WHEEL
print_extended-0.2.0.dist-info/entry_points.txt
print_extended-0.2.0.dist-info/top_level.txt
print_extended-0.2.0.dist-info/RECORD
