Metadata-Version: 2.1
Name: print-extended
Version: 0.2.0
Summary: Extended functionalities and better control over Python's built-in print function
Home-page: https://github.com/arrrlo/print-extended
Author: Amphinicy Technologies ltd
Author-email: info@amphinicy.com
License: MIT
Project-URL: Source, https://github.com/arrrlo/print-extended
Keywords: python,print,extended
Platform: UNKNOWN
Classifier: Development Status :: 4 - Beta
Classifier: Intended Audience :: Developers
Classifier: Topic :: Software Development :: Build Tools
Classifier: License :: OSI Approved :: MIT License
Classifier: Programming Language :: Python :: 3.7
Requires-Dist: click (~=7.0)
